[
    {
      "1Q21": "108518",
      "2Q21": "113080",
      "3Q21": "110812",
      "4Q21": "137412",
      "1Q22": "116444",
      "2Q22": "121234",
      "3Q22": "127101",
      "4Q22": "149204",
      "1Q23": "127358",
      "2Q23": "134383",
      "3Q23": "143083",
      "4Q23": "169961"
    },
    {
      "1Q21": "-13,6",
      "2Q21": "4,2",
      "3Q21": "-2,0",
      "4Q21": "24,0",
      "1Q22": "-15,3",
      "2Q22": "4,1",
      "3Q22": "4,8",
      "4Q22": "17,4",
      "1Q23": "-14,6",
      "2Q23": "5,5",
      "3Q23": "13,0",
      "4Q23": "18,8"
    },
    {
      "1Q21": "-17037",
      "2Q21": "4562",
      "3Q21": "-2268",
      "4Q21": "26600",
      "1Q22": "-20968",
      "2Q22": "4790",
      "3Q22": "5867",
      "4Q22": "22103",
      "1Q23": "-21846",
      "2Q23": "7025",
      "3Q23": "17528",
      "4Q23": "26878"
    },
    {
      "1Q21": "8107",
      "2Q21": "7778",
      "3Q21": "3156",
      "4Q21": "14323",
      "1Q22": "3844",
      "2Q22": "2028",
      "3Q22": "2872",
      "4Q22": "278",
      "1Q23": "3172",
      "2Q23": "6750",
      "3Q23": "9879",
      "4Q23": "10624"
    },
    {
      "1Q21": "42,5",
      "2Q21": "43,2",
      "3Q21": "43,2",
      "4Q21": "39,7",
      "1Q22": "42,9",
      "2Q22": "45,2",
      "3Q22": "44,7",
      "4Q22": "42,6",
      "1Q23": "46,8",
      "2Q23": "4804",
      "3Q23": "47,6",
      "4Q23": "45,5"
    }
  ]